{
  "model_name": "GBT",
  "train": {
    "accuracy": 0.9812,
    "weighted_f1": 0.9805,
    "cohen_kappa": 0.8420,
    "confusion_matrix": [
      [
        1831441,
        20560,
        915
      ],
      [
        10766,
        278484,
        2505
      ],
      [
        786,
        1856,
        25687
      ]
    ],
    "class_labels": [
      "Slight",
      "Serious",
      "Fatal"
    ],
    "per_class": {
      "Slight": {
        "precision": 0.9937,
        "recall": 0.9884,
        "f1": 0.9910
      },
      "Serious": {
        "precision": 0.9255,
        "recall": 0.9545,
        "f1": 0.9398
      },
      "Fatal": {
        "precision": 0.8825,
        "recall": 0.9068,
        "f1": 0.8945
      }
    }
  },
  "test": {
    "accuracy": 0.9724,
    "weighted_f1": 0.9718,
    "cohen_kappa": 0.8015,
    "confusion_matrix": [
      [
        457043,
        5088,
        471
      ],
      [
        6551,
        65147,
        1093
      ],
      [
        429,
        858,
        5862
      ]
    ],
    "class_labels": [
      "Slight",
      "Serious",
      "Fatal"
    ],
    "per_class": {
      "Slight": {
        "precision": 0.9850,
        "recall": 0.9880,
        "f1": 0.9865
      },
      "Serious": {
        "precision": 0.9164,
        "recall": 0.8950,
        "f1": 0.9056
      },
      "Fatal": {
        "precision": 0.7894,
        "recall": 0.8200,
        "f1": 0.8044
      }
    }
  }
}